DatasetsFactory/DatasetsFactory.py
DatasetsFactory/__init__.py
DatasetsFactory/usefull.py
datasetsfactory-0.4.dist-info/METADATA
datasetsfactory-0.4.dist-info/WHEEL
datasetsfactory-0.4.dist-info/licenses/LICENSE
datasetsfactory-0.4.dist-info/RECORD
