Metadata-Version: 2.3
Name: DatasetsFactory
Version: 0.4
Summary: This library is meant to DatasetsFactory app users, and is used for loading the available datasets locally!
Project-URL: GitHub, https://github.com/DenisAriton/DatasetsFactory_Library
Author-email: Denis Ariton <denis.ariton@student.upt.ro>
License: MIT License
License-File: LICENSE
Classifier: License :: OSI Approved :: MIT License
Classifier: Operating System :: OS Independent
Classifier: Programming Language :: Python :: 3
Requires-Python: >=3.12
Requires-Dist: requests
